ChangeLog.rst
LICENSE
MANIFEST.in
README.rst
setup.py
rstserv/__init__.py
rstserv/core.py
rstserv.egg-info/PKG-INFO
rstserv.egg-info/SOURCES.txt
rstserv.egg-info/dependency_links.txt
rstserv.egg-info/requires.txt
rstserv.egg-info/top_level.txt
rstserv/template/__init__.py
rstserv/template/default.css
scripts/rstserv
test/function_test.py