Metadata-Version: 1.1
Name: rstserv
Version: 0.1.0
Summary: Simple reStructured Text Viewer with HTTP Server
Home-page: https://github.com/unnonouno/rstserv
Author: Yuya Unno
Author-email: unnonouno@gmail.com
License: MIT
Platform: UNKNOWN
Classifier: Operating System :: OS Independent
Classifier: Environment :: Console
Classifier: Environment :: Web Environment
Classifier: Programming Language :: Python
Classifier: License :: OSI Approved :: MIT License
Classifier: Development Status :: 2 - Pre-Alpha
Classifier: Topic :: Utilities
